automata/__init__.py
automata/cli.py
automata/core.py
automata/utilities.py
automata_py-0.1a2.dist-info/entry_points.txt
automata_py-0.1a2.dist-info/LICENSE
automata_py-0.1a2.dist-info/WHEEL
automata_py-0.1a2.dist-info/METADATA
automata_py-0.1a2.dist-info/RECORD
