Metadata-Version: 2.1
Name: automata-py
Version: 0.1a2
Summary: A simple Python (3.10+) implementation aimed at simulating some cellular automata, primarily those focused on by Stephan Wolfram in his book "A New Kind of Science".
Author-email: Roy Levien <royl@msn.com>
Requires-Python: >=3.10,<4
Classifier: License :: OSI Approved :: MIT License
Classifier: Operating System :: MacOS
Classifier: Operating System :: Microsoft
Classifier: Operating System :: POSIX
Classifier: Intended Audience :: Other Audience
Classifier: Intended Audience :: End Users/Desktop
Classifier: Intended Audience :: Science/Research
Classifier: Programming Language :: Python :: 3.10
Classifier: Programming Language :: Python :: 3.11
Classifier: Programming Language :: Python :: 3.12
Classifier: Development Status :: 3 - Alpha
Classifier: Intended Audience :: Education
Classifier: Environment :: Console
Requires-Dist: numpy >=1.26
Requires-Dist: matplotlib >=3.8
Requires-Dist: ipywidgets ; extra == "all"
Requires-Dist: IPython ; extra == "all"
Requires-Dist: click ; extra == "all"
Requires-Dist: click ; extra == "cli"
Requires-Dist: ipywidgets ; extra == "notebook"
Requires-Dist: IPython ; extra == "notebook"
Project-URL: Home, https://github.com/orome/automata-py
Provides-Extra: all
Provides-Extra: cli
Provides-Extra: notebook
